mesh_decimator/__init__.py
mesh_decimator/decimator.py
mesh_decimator-0.1.0.dist-info/METADATA
mesh_decimator-0.1.0.dist-info/WHEEL
mesh_decimator-0.1.0.dist-info/top_level.txt
mesh_decimator-0.1.0.dist-info/RECORD
